wayflowcore/swarm.py
wayflowcore/transforms.py
wayflowcore/_metadata.py
wayflowcore/outputparser.py
wayflowcore/managerworkers.py
wayflowcore/componentwithio.py
wayflowcore/LICENSE-UPL.txt
wayflowcore/property.py
wayflowcore/LICENSE-APACHE.txt
wayflowcore/_proxyingmode.py
wayflowcore/conversation.py
wayflowcore/warnings.py
wayflowcore/conversationalcomponent.py
wayflowcore/THIRD_PARTY_LICENSES.txt
wayflowcore/messagelist.py
wayflowcore/stepdescription.py
wayflowcore/__init__.py
wayflowcore/flow.py
wayflowcore/flowhelpers.py
wayflowcore/ociagent.py
wayflowcore/flowconversation.py
wayflowcore/variable.py
wayflowcore/dataconnection.py
wayflowcore/agentconversation.py
wayflowcore/agent.py
wayflowcore/planning.py
wayflowcore/py.typed
wayflowcore/exceptions.py
wayflowcore/_threading.py
wayflowcore/tokenusage.py
wayflowcore/component.py
wayflowcore/controlconnection.py
wayflowcore/idgeneration.py
wayflowcore/_utils/async_helpers.py
wayflowcore/_utils/dataclass_utils.py
wayflowcore/_utils/lazy_loader.py
wayflowcore/_utils/__init__.py
wayflowcore/_utils/formatting.py
wayflowcore/_utils/print.py
wayflowcore/_utils/singleton.py
wayflowcore/_utils/io_utils.py
wayflowcore/_utils/_templating_helpers.py
wayflowcore/_utils/json_correction.py
wayflowcore/embeddingmodels/openaicompatiblemodel.py
wayflowcore/embeddingmodels/embeddingmodel.py
wayflowcore/embeddingmodels/__init__.py
wayflowcore/embeddingmodels/vllmmodel.py
wayflowcore/embeddingmodels/ollamamodel.py
wayflowcore/embeddingmodels/openaimodel.py
wayflowcore/embeddingmodels/ocigenaimodel.py
wayflowcore/tracing/trace.py
wayflowcore/tracing/spanexporter.py
wayflowcore/tracing/spanprocessor.py
wayflowcore/tracing/__init__.py
wayflowcore/tracing/span.py
wayflowcore/tracing/opentelemetry/spanprocessor.py
wayflowcore/tracing/opentelemetry/__init__.py
wayflowcore/tracing/opentelemetry/span.py
wayflowcore/agentspec/_agentspecconverter.py
wayflowcore/agentspec/runtimeloader.py
wayflowcore/agentspec/__init__.py
wayflowcore-25.4.3.dist-info/RECORD
wayflowcore-25.4.3.dist-info/LICENSE-UPL.txt
wayflowcore-25.4.3.dist-info/LICENSE-APACHE.txt
wayflowcore-25.4.3.dist-info/THIRD_PARTY_LICENSES.txt
wayflowcore-25.4.3.dist-info/WHEEL
wayflowcore-25.4.3.dist-info/top_level.txt
wayflowcore-25.4.3.dist-info/METADATA
